spiderai/__init__.py
spiderai/ai_processor.py
spiderai/extractor.py
spiderai-0.1.0.dist-info/METADATA
spiderai-0.1.0.dist-info/WHEEL
spiderai-0.1.0.dist-info/licenses/LICENSE
spiderai-0.1.0.dist-info/RECORD
