Metadata-Version: 2.3
Name: spiderai
Version: 0.1.0
Summary: A Python library for extracting structured data from web pages using AI.
Project-URL: Homepage, https://github.com/AB7zz/web_extractor
Project-URL: Issues, https://github.com/AB7zz/web_extractor/issues
Author-email: Abhinav C V <abhinavcv007@gmail.com>
Classifier: License :: OSI Approved :: MIT License
Classifier: Operating System :: OS Independent
Classifier: Programming Language :: Python :: 3
Requires-Python: >=3.10
Requires-Dist: absl-py==2.1.0
Requires-Dist: annotated-types==0.7.0
Requires-Dist: beautifulsoup4==4.12.3
Requires-Dist: cachetools==5.5.0
Requires-Dist: google-ai-generativelanguage==0.6.10
Requires-Dist: google-api-core==2.23.0
Requires-Dist: google-api-python-client==2.154.0
Requires-Dist: google-auth-httplib2==0.2.0
Requires-Dist: google-auth==2.36.0
Requires-Dist: google-generativeai==0.8.3
Requires-Dist: pydantic==2.10.2
Requires-Dist: python-dotenv==1.0.1
Requires-Dist: requests==2.32.3
Requires-Dist: tqdm==4.67.1
